{
    "name": "custom-checkbox-parameter",
    "installations": {
        "1593576000000": 27
    },
    "installationsPercentage": {
        "1593576000000": 0.00953682805099024
    },
    "installationsPerVersion": {
        "1.0": 25,
        "1.0-SNAPSHOT (private)": 1,
        "1.2-SNAPSHOT (private)": 1
    },
    "installationsPercentagePerVersion": {
        "1.0": 0.008830396343509482,
        "1.0-SNAPSHOT (private)": 3.5321585374037927E-4,
        "1.2-SNAPSHOT (private)": 3.5321585374037927E-4
    }
}