{
    "name": "database-mariadb",
    "installations": {
        "1701388800000": 6,
        "1704067200000": 8,
        "1706745600000": 13
    },
    "installationsPercentage": {
        "1701388800000": 0.0021161558,
        "1704067200000": 0.0027592392,
        "1706745600000": 0.0045548826
    },
    "installationsPerVersion": {
        "35.va_ea_62c1d0f0a_": 12,
        "7.v87646a_8a_7b_b_7": 1
    },
    "installationsPercentagePerVersion": {
        "35.va_ea_62c1d0f0a_": 0.0042045075,
        "7.v87646a_8a_7b_b_7": 0.0003503756
    }
}