{
    "name": "multibranch-action-triggers",
    "installations": {
        "1567310400000": 70
    },
    "installationsPercentage": {
        "1567310400000": 0.02633182614976038
    },
    "installationsPerVersion": {
        "1.2": 13,
        "1.3": 55,
        "1.3-SNAPSHOT (private)": 1,
        "1.4": 1
    },
    "installationsPercentagePerVersion": {
        "1.2": 0.0048901962849555,
        "1.3": 0.020689291974811726,
        "1.3-SNAPSHOT (private)": 3.761689449965769E-4,
        "1.4": 3.761689449965769E-4
    }
}