{
    "name": "qualys-iac-security",
    "installations": {
        "1672531200000": 1,
        "1675209600000": 5,
        "1677628800000": 4,
        "1682899200000": 4
    },
    "installationsPercentage": {
        "1672531200000": 0.00034045335,
        "1675209600000": 0.001643769,
        "1677628800000": 0.0012469839,
        "1682899200000": 0.0014945058
    },
    "installationsPerVersion": {
        "1.0.0": 4
    },
    "installationsPercentagePerVersion": {
        "1.0.0": 0.0014945058
    }
}