{
    "name": "vectorcast-execution",
    "installations": {
        "1477958400000": 4
    },
    "installationsPercentage": {
        "1477958400000": 0.0029299950922582205
    },
    "installationsPerVersion": {
        "0.10": 1,
        "0.11-SNAPSHOT (private)": 1,
        "0.9": 1,
        "1.0-SNAPSHOT (private)": 1
    },
    "installationsPercentagePerVersion": {
        "0.10": 7.324987730645551E-4,
        "0.11-SNAPSHOT (private)": 7.324987730645551E-4,
        "0.9": 7.324987730645551E-4,
        "1.0-SNAPSHOT (private)": 7.324987730645551E-4
    }
}