{
    "name": "violation-comments-to-github",
    "installations": {
        "1456790400000": 22,
        "1459468800000": 63
    },
    "installationsPercentage": {
        "1456790400000": 0.020085821236190998,
        "1459468800000": 0.051057208386349084
    },
    "installationsPerVersion": {
        "1.10": 5,
        "1.4": 1,
        "1.5": 16,
        "1.6": 4,
        "1.7": 2,
        "1.7-SNAPSHOT (private)": 1,
        "1.8": 22,
        "1.8-SNAPSHOT (private)": 1,
        "1.9": 11
    },
    "installationsPercentagePerVersion": {
        "1.10": 0.004052159395741991,
        "1.4": 8.104318791483982E-4,
        "1.5": 0.012966910066374371,
        "1.6": 0.003241727516593593,
        "1.7": 0.0016208637582967964,
        "1.7-SNAPSHOT (private)": 8.104318791483982E-4,
        "1.8": 0.01782950134126476,
        "1.8-SNAPSHOT (private)": 8.104318791483982E-4,
        "1.9": 0.00891475067063238
    }
}